{
"icons": [
    {
      "name": "genghisliu",
      "url": "https://bhsv1.xyz/i/2024/07/03/oxdpcc.png"
    },
    {
      "name": "Yahoo Japan",
      "url": "https://raw.githubusercontent.com/genghisliuhaha/-/main/IMG_0242.png"
    },
    {
      "name": "Wise",
      "url": "https://bhsv1.xyz/i/2024/07/03/p0ibl4.png"
    },
    {
      "name": "PayPay",
      "url": "https://bhsv1.xyz/i/2024/07/03/p0iq4h.png"
    },
    {
      "name": "Papara",
      "url": "https://bhsv1.xyz/i/2024/07/03/p0ivjg.png"
    },
{
      "name": "1Password",
      "url": "https://bhsv1.xyz/i/2024/07/03/p59r86.png"
    }
  ]
}
